sonya/__init__.py
sonya/db.py
sonya/db.pyi
sonya/document.py
sonya/document.pyi
sonya/env.py
sonya/env.pyi
sonya/schema.py
sonya/schema.pyi
sonya/sophia.c
sonya/sophia.cpython-36m-arm-linux-gnueabihf.so
sonya/sophia.pyi
sonya/sophia.pyx
sonya/fields/__init__.py
sonya/fields/base.py
sonya/fields/base.pyi
sonya/fields/bytes_field.py
sonya/fields/bytes_field.pyi
sonya/fields/enum_field.py
sonya/fields/enum_field.pyi
sonya/fields/float_field.py
sonya/fields/float_field.pyi
sonya/fields/integer_field.py
sonya/fields/integer_field.pyi
sonya/fields/ip_field.py
sonya/fields/ip_field.pyi
sonya/fields/json_field.py
sonya/fields/json_field.pyi
sonya/fields/msgpack_field.py
sonya/fields/msgpack_field.pyi
sonya/fields/pickle_field.py
sonya/fields/pickle_field.pyi
sonya/fields/uuid_field.py
sonya/fields/uuid_field.pyi
sonya/src/sophia.c
sonya/src/sophia.h
sonya-0.6.6.dist-info/DESCRIPTION.rst
sonya-0.6.6.dist-info/METADATA
sonya-0.6.6.dist-info/RECORD
sonya-0.6.6.dist-info/WHEEL
sonya-0.6.6.dist-info/metadata.json
sonya-0.6.6.dist-info/top_level.txt
