Metadata-Version: 2.0
Name: sonya
Version: 0.6.6
Summary: Python bindings for the sophia database.
Home-page: UNKNOWN
Author: Dmitry Orlov
Author-email: me@mosquito.su
License: BSD
Platform: UNKNOWN
Classifier: License :: OSI Approved :: BSD License
Classifier: Topic :: Software Development
Classifier: Topic :: Software Development :: Libraries
Classifier: Intended Audience :: Developers
Classifier: Natural Language :: English
Classifier: Operating System :: MacOS
Classifier: Operating System :: POSIX
Classifier: Programming Language :: Python
Classifier: Programming Language :: Python :: 2.7
Classifier: Programming Language :: Python :: 3
Classifier: Programming Language :: Python :: 3.4
Classifier: Programming Language :: Python :: 3.5
Classifier: Programming Language :: Python :: 3.6
Classifier: Programming Language :: Python :: Implementation :: CPython
Requires-Python: >=2.7.*, <4
Requires-Dist: six
Requires-Dist: enum34; python_version < "3"
Requires-Dist: py2-ipaddress; python_version < "3"
Provides-Extra: develop
Requires-Dist: Cython; extra == 'develop'
Requires-Dist: backports.tempfile; extra == 'develop'
Requires-Dist: msgpack-python; extra == 'develop'
Requires-Dist: pytest; extra == 'develop'
Provides-Extra: msgpack
Requires-Dist: msgpack-python; extra == 'msgpack'
